controlpyweb/__init__.py
controlpyweb/abstract_reader_writer.py
controlpyweb/errors.py
controlpyweb/reader_writer.py
controlpyweb/webio_module.py
controlpyweb/io/__init__.py
controlpyweb/io/analog_io.py
controlpyweb/io/discrete_io.py
controlpyweb/io/io_out.py
controlpyweb/io/single_io.py
controlpyweb/io_definitions/__init__.py
controlpyweb/io_definitions/analog_io.py
controlpyweb/io_definitions/discrete_io.py
controlpyweb/io_definitions/io_out.py
controlpyweb/io_definitions/single_io.py
tests/__init__.py
tests/test_overloads.py
tests/test_read_write.py
tests/test_single_io.py
controlpyweb-0.1.0.dist-info/LICENSE.txt
controlpyweb-0.1.0.dist-info/METADATA
controlpyweb-0.1.0.dist-info/WHEEL
controlpyweb-0.1.0.dist-info/top_level.txt
controlpyweb-0.1.0.dist-info/RECORD
