Metadata-Version: 2.1
Name: controlpyweb
Version: 0.1.0
Summary: A project to facilitate easy read/write to the ControlByWeb line of Automation/SCADA IO products.
Home-page: https://github.com/washad/ControlPyWeb
Author: Steve Jackson
Author-email: washad@gmail.com
License: UNKNOWN
Platform: UNKNOWN
Classifier: Programming Language :: Python :: 3
Classifier: License :: OSI Approved :: MIT License
Classifier: Operating System :: OS Independent
Requires-Dist: wheel
Requires-Dist: requests
Requires-Dist: str2bool
